{
  "required": true,
  "minVersion": "0.8",
  "package": "io.github.dracosomething.trawakened.mixin",
  "compatibilityLevel": "JAVA_8",
  "refmap": "trawakened.refmap.json",
  "mixins": [
    "FlyingPathNavigationMixin",
    "ForgeEventFactoryMixin",
    "GluttonyMistProjectileMixin",
    "JumpingEntityMoveControlMixin",
    "LivingEntityMixin",
    "LookControlMixin",
    "MobMixin",
    "OnTickHandlerMixin",
    "PathNavigationMixin",
    "RaceSelectionMenuMixin",
    "SlimeEntityMixin",
    "SupermassiveSlimeEntityMixin",
    "TensuraPlayerCapabilityMixin",
    "UtilMixin"
  ],
  "client": [
    "KeyboardMixin",
    "MouseHandlerMixin",
    "TimerMixin"
  ],
  "injectors": {
    "defaultRequire": 1
  }
}
